<xml xmlns:o="urn:schemas-microsoft-com:office:office">
 <o:MainFile HRef="../PSP-MissingParts.htm"/>
 <o:File HRef="PSP-MissingParts_30971_image001.png"
  PublicationID="PSP-MissingParts_30971"/>
 <o:File HRef="PSP-MissingParts_30971_image002.png"
  PublicationID="PSP-MissingParts_30971"/>
 <o:File HRef="PSP-MissingParts_30971_image003.png"
  PublicationID="PSP-MissingParts_30971"/>
 <o:File HRef="PSP-MissingParts_30971_image004.png"
  PublicationID="PSP-MissingParts_30971"/>
 <o:File HRef="PSP-MissingParts_30971_image005.png"
  PublicationID="PSP-MissingParts_30971"/>
 <o:File HRef="PSP-MissingParts_30971_image006.png"
  PublicationID="PSP-MissingParts_30971"/>
 <o:File HRef="PSP-MissingParts_30971_image007.png"
  PublicationID="PSP-MissingParts_30971"/>
 <o:File HRef="PSP-MissingParts_30971_image008.png"
  PublicationID="PSP-MissingParts_30971"/>
 <o:File HRef="PSP-MissingParts_30971_image009.png"
  PublicationID="PSP-MissingParts_30971"/>
 <o:File HRef="PSP-MissingParts_30971_image010.png"
  PublicationID="PSP-MissingParts_30971"/>
 <o:File HRef="filelist.xml"/>
</xml>